openslides_protocol/__init__.py
openslides_protocol/access_permissions.py
openslides_protocol/apps.py
openslides_protocol/config_variables.py
openslides_protocol/models.py
openslides_protocol/serializers.py
openslides_protocol/signals.py
openslides_protocol/views.py
openslides_protocol/locale/angular-gettext/de.po
openslides_protocol/locale/angular-gettext/ru.po
openslides_protocol/locale/angular-gettext/template-en.pot
openslides_protocol/migrations/0001_initial.py
openslides_protocol/migrations/__init__.py
openslides_protocol/static/i18n/openslides_protocol/de.json
openslides_protocol/static/i18n/openslides_protocol/ru.json
openslides_protocol/static/js/openslides_protocol/base.js
openslides_protocol/static/js/openslides_protocol/site.js
openslides_protocol/static/js/openslides_protocol/templatehooks.js
openslides_protocol/static/js/openslides_protocol/templates.js
openslides_protocol/static/templates/openslides_protocol/agenda-hook.html
openslides_protocol/static/templates/openslides_protocol/assignment-detail-hook.html
openslides_protocol/static/templates/openslides_protocol/assignment-list-hook.html
openslides_protocol/static/templates/openslides_protocol/motion-detail-hook.html
openslides_protocol/static/templates/openslides_protocol/motion-list-hook.html
openslides_protocol/static/templates/openslides_protocol/object-protocol-form.html
openslides_protocol/static/templates/openslides_protocol/protocol-list.html
openslides_protocol/static/templates/openslides_protocol/topic-detail-hook.html
openslides_protocol-1.0.dist-info/METADATA
openslides_protocol-1.0.dist-info/RECORD
openslides_protocol-1.0.dist-info/WHEEL
openslides_protocol-1.0.dist-info/entry_points.txt
openslides_protocol-1.0.dist-info/top_level.txt
